xflrpy/__init__.py
xflrpy/client.py
xflrpy/types.py
xflrpy/utils.py
xflrpy-0.4.0.dist-info/LICENSE
xflrpy-0.4.0.dist-info/METADATA
xflrpy-0.4.0.dist-info/WHEEL
xflrpy-0.4.0.dist-info/top_level.txt
xflrpy-0.4.0.dist-info/RECORD
