Metadata-Version: 2.1
Name: xflrpy
Version: 0.4.0
Summary: A python client for design optimization and scripting with XFLR5
Home-page: https://github.com/nikhil-sethi/xflrpy
Author: Nikhil Sethi
Author-email: sethi.nirvil@gmail.com
License: GPLv3
Platform: UNKNOWN
Classifier: Programming Language :: Python :: 3
Classifier: License :: OSI Approved :: GNU General Public License v3 (GPLv3)
Classifier: Operating System :: OS Independent
License-File: LICENSE
Requires-Dist: msgpack-rpc-python
